pimmi/__init__.py
pimmi/clusters.py
pimmi/download_demo.py
pimmi/eval.py
pimmi/pimmi.py
pimmi/pimmi_parameters.py
pimmi/sift_create.py
pimmi/toolbox.py
pimmi/cli/__init__.py
pimmi/cli/__main__.py
pimmi/cli/config.py
pimmi/cli/config.yml
test/__init__.py
test/dataset_test.py
test/pipeline_test.py
test/sift_test.py
test/toolbox_test.py
test/utils.py
pimmi-0.4.0.dist-info/LICENSE
pimmi-0.4.0.dist-info/METADATA
pimmi-0.4.0.dist-info/WHEEL
pimmi-0.4.0.dist-info/entry_points.txt
pimmi-0.4.0.dist-info/top_level.txt
pimmi-0.4.0.dist-info/zip-safe
pimmi-0.4.0.dist-info/RECORD
