Metadata-Version: 2.1
Name: pimmi
Version: 0.4.0
Summary: Python IMage MIning
Home-page: http://github.com/nrv/pimmi
Author: Nicolas Hervé
Author-email: 
License: GPL-3.0
Keywords: image mining
Requires-Python: >=3.8
License-File: LICENSE
Requires-Dist: casanova
Requires-Dist: faiss-cpu
Requires-Dist: fog
Requires-Dist: networkx (<3,>=2.7)
Requires-Dist: opencv-python
Requires-Dist: pyyaml
Requires-Dist: tqdm
